lnschema_bionty/__init__.py
lnschema_bionty/_bionty.py
lnschema_bionty/ids.py
lnschema_bionty/models.py
lnschema_bionty/core/__init__.py
lnschema_bionty/core/_add_ontology.py
lnschema_bionty/core/_bionty.py
lnschema_bionty/core/_settings.py
lnschema_bionty/migrations/0023_rename_publicsource_encode_uid.py
lnschema_bionty/migrations/0024_remove_cellline_collections_and_more.py
lnschema_bionty/migrations/0025_artifactcellline_alter_cellline_artifacts_and_more.py
lnschema_bionty/migrations/0026_artifactcellline_cell_line_ref_is_name_and_more.py
lnschema_bionty/migrations/0027_remove_artifactcellline_created_at_and_more.py
lnschema_bionty/migrations/0028_artifactcellline_created_at_and_more.py
lnschema_bionty/migrations/0028_squashed.py
lnschema_bionty/migrations/0029_alter_cellline_previous_runs_and_more.py
lnschema_bionty/migrations/0030_rename_publicsource_source_and_more.py
lnschema_bionty/migrations/__init__.py
lnschema_bionty-0.44.0.dist-info/LICENSE
lnschema_bionty-0.44.0.dist-info/WHEEL
lnschema_bionty-0.44.0.dist-info/METADATA
lnschema_bionty-0.44.0.dist-info/RECORD
