Metadata-Version: 2.1
Name: lnschema_bionty
Version: 0.44.0
Summary: Registries for basic biological entities, coupled to public ontologies.
Author-email: Lamin Labs <laminlabs@gmail.com>
Classifier: License :: OSI Approved :: Apache Software License
Classifier: Programming Language :: Python :: 3.8
Classifier: Programming Language :: Python :: 3.9
Classifier: Programming Language :: Python :: 3.10
Requires-Dist: lnschema_core>=0.69.0
Requires-Dist: bionty_base==0.38.0
Requires-Dist: pre-commit ; extra == "test"
Requires-Dist: nox ; extra == "test"
Requires-Dist: requests ; extra == "test"
Requires-Dist: pytest>=6.0 ; extra == "test"
Requires-Dist: pytest-cov ; extra == "test"
Requires-Dist: nbproject-test ; extra == "test"
Project-URL: Home, https://github.com/laminlabs/lnschema-bionty
Provides-Extra: test
